{"user_rating": 3.0, "review_count": 7, "name": "Christos Studios", "reviews": [{"rating": 2.0, "stay_parameters": "Stayed August 2008, traveled as a couple", "text": "Just returned from 2 weeks at the Christos - the location of these apartments is fantastic, right on the waterfront and about 3 minutes walk from the bars & restaurants.", "title": "they were OK", "helpfulness": 2, "user": "JanLovedSF", "date": "September 8, 2008", "detail_rating": {"cleanliness": 2.0, "value": 2.0, "location": 5.0, "service": 1.0, "rooms": 2.0}, "id": 19871161, "likes": {"liked": "\u2014 location", "disliked": "\u2014 no shower/ toilet facilities on the last day"}}, {"rating": 3.0, "stay_parameters": "Stayed June 2008, traveled as a couple", "text": "The rooms at Christos vary in size immensley - some are pretty good, others (like ours- room 7) are pretty small - we couldnt open the patio doors fully as the bed was in the way, and couldnt open the wardrobe fully as the bed was in the way, the bathroom door couldn't be opened more than half way, as it would hit the sink (you get the picture!) - the room was adequate for our needs and the bathroom even had a shower curtain ! (the bathroom flooded every time we had a shower, but thats why they all have plugholes in the floor - I've never had a Greek bathroom that didnt flood.", "title": "A good example of a Greek apartment", "helpfulness": 3, "user": "Sonnygirl33", "date": "June 8, 2008", "detail_rating": {"cleanliness": 3.0, "value": 4.0, "location": 5.0, "service": 3.0, "rooms": 3.0}, "id": 16762946, "likes": {"liked": "\u2014 Location", "disliked": "\u2014 No Lift"}}], "location": {"country": "Greece", "continent": "Europe"}, "variance": {"poor": 1, "average": 2, "very good": 3, "terrible": 1, "excellent": 0}, "slim_ranking": 0.756756756757}