{"user_rating": 4.5, "review_count": 129, "name": "Domus Mariae Benessere", "reviews": [{"rating": 5.0, "stay_parameters": "Stayed October 2013, traveled as a couple", "text": "Out our window was the sea. If one had time, the spa sang a siren's song, and the quiet ladies of the convent smiled and offered assistance when we met in the elevator. In addition to a great location, we had a tasty breakfast, and nighttime wine on the rooftop, from which the lights of Syracusa winked. We were close to the Ancient Greek Temples and Italian designer clothing boutiques. In a word. We had it all.", "title": "The Convent, Spa, Hotel Experience in Ortygia", "user": "JJtheScrivener", "date": "November 17, 2013", "detail_rating": {"service": 5.0, "cleanliness": 5.0, "value": 5.0, "sleep": 5.0, "rooms": 5.0, "location": 5.0}, "id": 185018137}, {"rating": 4.0, "stay_parameters": "Stayed September 2013, traveled solo", "text": "The room I stayed in had a sea view and was elegantly furnished.", "title": "Beautiful room and very pleasant staff", "user": "rubypink", "date": "October 30, 2013", "detail_rating": {"service": 4.0, "cleanliness": 4.0, "value": 4.0, "sleep": 4.0, "rooms": 4.0, "location": 4.0}, "id": 182978855}, {"rating": 5.0, "stay_parameters": "Stayed September 2013, traveled as a couple", "text": "Free bikes were available on request and very much added to the pleasure of my trip. Breakfast was ample and varied.", "title": "Excellent in all respects; location, views, breakfast", "helpfulness": 1, "user": "mikephelan", "date": "October 26, 2013", "detail_rating": {"service": 5.0, "cleanliness": 5.0, "value": 5.0, "sleep": 5.0, "rooms": 5.0, "location": 5.0}, "id": 182484397}, {"rating": 5.0, "title": "Peace and tranquility", "text": "The staff were attentive and helpful without being intrusive.", "user": "SimonNS", "date": "October 26, 2013", "id": 182425039}, {"rating": 5.0, "stay_parameters": "Stayed October 2013, traveled as a couple", "text": "Rooms were large and well appointed, Bathroom was larger than most and the location is terrific, right near the water. We used the parking facilities provided and walked everywhere we went, even to the Ruins. Spent almost all of our two days on the island so the car park was important.", "title": "Beautiful place", "user": "Deckrail", "date": "October 22, 2013", "detail_rating": {"service": 5.0, "cleanliness": 5.0, "value": 5.0, "sleep": 5.0, "rooms": 5.0, "location": 5.0}, "id": 182013550}], "location": {"country": "Italy", "continent": "Europe"}, "stars": 3, "variance": {"poor": 2, "average": 4, "very good": 46, "terrible": 1, "excellent": 76}, "aka": "Domus Mariae Benessere Sicily/Syracuse, Italy", "slim_ranking": 0.0625}