{"user_rating": 4.0, "review_count": 175, "name": "Eurostars Montgomery", "reviews": [{"rating": 2.0, "stay_parameters": "Stayed October 2013, traveled with family", "text": "I stayed overnight in this hotel a week ago and cannot believe how it could have a 5 Star rating.", "title": "Not 5 Star Hotel - not by a long shot!", "helpfulness": 1, "user": "jeancan", "date": "October 12, 2013", "detail_rating": {"service": 1.0, "cleanliness": 5.0, "value": 2.0, "sleep": 5.0, "rooms": 2.0, "location": 5.0}, "id": 180711873}, {"rating": 4.0, "stay_parameters": "Stayed August 2013, traveled on business", "text": "My room was lovely and delightfully quiet but my sister's room was worn, tatty with lightbulbs missing and fittings hanging loose over the bed and a huge worn area in the carpet inside the door. We phoned ahead from the airport to ask how late food was served and were told it was served til 11pm. On arrival before 10pm the waiter in the foyer told us that the kitchen closed at 10pm. We insisted that we had been told otherwise on the phone half an hour beforehand and eventually got Spag Bol and Veg Lasagne served to us with very little grace.", "title": "Good comfortable hotel in Brussels", "user": "RVivekanand", "date": "September 28, 2013", "detail_rating": {"service": 4.0, "cleanliness": 4.0, "value": 4.0, "sleep": 4.0, "rooms": 4.0, "location": 3.0}, "id": 178913101}, {"rating": 5.0, "stay_parameters": "Stayed May 2013, traveled on business", "text": "The hotel does NOT have a Bar and a sullen waiter reluctantly carried out drinks to my group.There was difficulty in getting a cup of tea without seeming to be an intrusion and being told the kitchen was closed during the afternoon when our group needed tea. Breakfast was great, lovely food buffet. There is no diningroom as such, the food being served in what is basically a corridor / foyer. How can a hotel have 5 Stars when it has no Bar and no proper diningroom and restricted hours of service? The location of the hotel is excellent.", "title": "Great hotel! Excellent choice!", "user": "Stacey A", "date": "September 3, 2013", "detail_rating": {"service": 5.0, "cleanliness": 5.0, "value": 5.0, "sleep": 5.0, "rooms": 5.0, "location": 5.0}, "id": 175451683}, {"rating": 3.0, "stay_parameters": "Stayed August 2013, traveled on business", "text": "This is a very good compact yet comfortable hotel in Brussels", "title": "Ok but tired", "user": "Jeroen22", "date": "September 3, 2013", "detail_rating": {"service": 4.0, "cleanliness": 3.0, "value": 3.0, "sleep": 3.0, "rooms": 3.0, "location": 3.0}, "id": 175418333}, {"rating": 4.0, "stay_parameters": "Stayed August 2013, traveled on business", "text": "Easy access, not far from the airport and from Businesses and Offices", "title": "Good hotel", "helpfulness": 1, "user": "flyingdutchmannl", "date": "August 30, 2013", "detail_rating": {"service": 5.0, "cleanliness": 3.0, "value": 4.0, "sleep": 4.0, "rooms": 3.0, "location": 3.0}, "id": 174812452}], "location": {"country": "Belgium", "continent": "Europe", "city": "Woluwe-St-Pierre"}, "stars": 5, "variance": {"poor": 16, "average": 39, "very good": 66, "terrible": 4, "excellent": 50}, "aka": "Eurostars Montgomery Hotel Woluwe-St-Pierre", "slim_ranking": 1.0}