{"user_rating": 5.0, "review_count": 9, "name": "George Alexander House", "reviews": [{"rating": 4.0, "stay_parameters": "Stayed May 2007, traveled as a couple", "text": "I've been to Healdsburg a few times and always like to try new properties, so selected this B&B for a 2-night stay on the advice of a friend. Overall, I was very pleased, and the only thing that prevents me from giving this place 5 stars is the bathrooms.", "title": "Charming B&B, solid experience", "helpfulness": 1, "user": "soljc", "date": "May 15, 2007", "detail_rating": {"front_desk": 4.0, "business": 3.0, "service": 5.0, "cleanliness": 4.0, "value": 4.0, "location": 4.0, "rooms": 4.0}, "id": 7626564, "likes": {"liked": "\u2014 Location, breakfasts, staff", "disliked": "\u2014 bathroom"}}], "location": {"country": "United States"}, "variance": {"poor": 0, "average": 0, "very good": 2, "terrible": 0, "excellent": 7}, "slim_ranking": 0.875}