{"user_rating": 4.0, "review_count": 29, "name": "Holiday Inn Express Warren", "reviews": [{"rating": 5.0, "stay_parameters": "Stayed September 2006, traveled on business", "text": "Spotless rooms, well lit, nice linens, very comfortable.", "title": "Great place to stay", "helpfulness": 1, "user": "Snarky", "date": "September 22, 2006", "detail_rating": {"front_desk": 5.0, "business": 5.0, "service": 5.0, "cleanliness": 5.0, "value": 5.0, "location": 4.0, "rooms": 5.0}, "id": 5821619, "likes": {"liked": "\u2014 They do offer discounted rates for area companies, so it's worth calling the hotel direct to ask before you book."}}, {"rating": 4.0, "stay_parameters": "Stayed February 2006, traveled on business", "text": "The high speed internet access works without a problem, too.", "title": "Friendly Staff..would recommend.", "helpfulness": 2, "user": "CRSTS", "date": "March 20, 2006", "detail_rating": {"cleanliness": 4.0, "value": 4.0, "rooms": 4.0, "service": 4.0}, "id": 4706842}], "location": {"country": "United States", "city": "Warren"}, "stars": 3, "variance": {"poor": 1, "average": 6, "very good": 14, "terrible": 0, "excellent": 8}, "aka": "Holiday Inn Express Warren Hotel Warren", "slim_ranking": 0.631578947368, "description": "Welcome to the Holiday Inn Express Detroit/Warren. Recently renovated to satisfy your travel needs, our 124 guest rooms and 21 Jacuzzi rooms feature a fresh new look, luxurious beds, a much larger work space and much improved lighting. Start your day with our complimentary, hot buffet breakfast and relax in the evening with friends or co-workers in our Great Room, which features a fireplace and a big, flat screen TV. Enjoy a full complimentary dinner Monday-Wednesday. We have a 24 hour business center with high-speed Internet access, a FAX, printer and plenty of work space. We are conveniently located close to General Motors, DaimlerChrysler, Tacom, General Dynamics, and we are the only hotel called the Holiday Inn Express GM Tech Center."}