{"user_rating": 3.0, "review_count": 294, "name": "Hotel Mercure Leblon", "reviews": [{"rating": 3.0, "stay_parameters": "Stayed October 2012", "text": "The service is quite below international level, as usual for Rio. And it's an Accor Mercure. The room has a bathroom with no windows or ventilation. It smells bad.", "title": "Bad service: too expensive despite well localized", "user": "RenatoBeani", "date": "October 13, 2012", "detail_rating": {"cleanliness": 2.0, "value": 3.0, "location": 4.0, "service": 2.0, "rooms": 3.0}, "id": 142734116}, {"rating": 3.0, "stay_parameters": "Stayed September 2012, traveled with friends", "text": "The management said they are changing all plumbing and elevators, but I don't think it will solve the smell.", "title": "BEST LOCATION AND SOMETHING ELSE!", "helpfulness": 1, "user": "DamianSadovsky", "date": "September 3, 2012", "detail_rating": {"service": 5.0, "cleanliness": 4.0, "value": 3.0, "sleep": 4.0, "rooms": 3.0, "location": 5.0}, "id": 139293081}, {"rating": 2.0, "stay_parameters": "Stayed August 2012, traveled solo", "text": "Regarding elevators, there is no service one, so me and my family had to stay once with garbage, other times with hotel people full of boxes or minibar stuff. Just ugly.", "title": "Another Rio de Janeiro rip-off", "user": "Salvador2011", "date": "August 22, 2012", "detail_rating": {"service": 3.0, "cleanliness": 2.0, "value": 2.0, "sleep": 2.0, "rooms": 2.0, "location": 4.0}, "id": 137987492}, {"rating": 3.0, "title": "Good hotel in good location shame about the poor common areas.", "text": "It's good to stay near the beach, so I didn't care about the 80's decoration style.", "user": "A TripAdvisor user", "date": "August 2, 2012", "id": 136027833}, {"rating": 3.0, "stay_parameters": "Stayed May 2012, traveled with family", "text": "I have been staying at this hotel for over a month now. What can I say?", "title": "Great location. The rest....not so much", "user": "Tanya M", "date": "May 28, 2012", "detail_rating": {"service": 2.0, "cleanliness": 2.0, "value": 2.0, "sleep": 2.0, "rooms": 3.0, "location": 5.0}, "id": 130778011}, {"rating": 4.0, "stay_parameters": "Stayed April 2012, traveled with family", "text": "Good points :", "title": "Great for a family.", "helpfulness": 4, "user": "Amanda H", "date": "May 4, 2012", "detail_rating": {"service": 4.0, "cleanliness": 4.0, "value": 5.0, "sleep": 4.0, "rooms": 4.0, "location": 4.0}, "id": 129361069}, {"rating": 3.0, "title": "not a \"comfort-first\" kind of hotel, but one thing: location", "text": "- fantastic location, close to the beach, shopping mall, restaurants, bus stop etc", "user": "A TripAdvisor user", "date": "April 23, 2012", "id": 128417216}, {"rating": 2.0, "title": "Run down", "text": "- decent coffee in the lobby", "user": "A TripAdvisor user", "date": "March 24, 2012", "id": 126581491}, {"rating": 2.0, "stay_parameters": "Stayed March 2012, traveled on business", "text": "-nice view from my balcony", "title": "poor service", "helpfulness": 2, "user": "Corrado_C", "date": "March 20, 2012", "detail_rating": {"service": 1.0, "cleanliness": 2.0, "value": 2.0, "sleep": 2.0, "rooms": 3.0, "location": 4.0}, "id": 126394220}, {"rating": 3.0, "stay_parameters": "Stayed January 2012, traveled with family", "text": "we were a group of 4 adults. stayed in a 2 bed suite, which consisted of a livinig room, small kitchenete, dining area, twin bedroom, shower room, double bed with ensute shower.", "title": "Location & Practicality", "helpfulness": 2, "user": "honestreviewuk", "date": "January 23, 2012", "detail_rating": {"service": 2.0, "cleanliness": 4.0, "value": 3.0, "sleep": 4.0, "rooms": 4.0, "location": 5.0}, "id": 123518822}, {"rating": 3.0, "stay_parameters": "Stayed January 2012, traveled solo", "text": "positives;", "title": "Rio De Janeiro Vacation Jan 4-11, 2012", "helpfulness": 2, "user": "princzz", "date": "January 14, 2012", "detail_rating": {"service": 5.0, "cleanliness": 4.0, "value": 3.0, "sleep": 5.0, "rooms": 5.0, "location": 5.0}, "id": 123056971}, {"rating": 2.0, "stay_parameters": "Stayed January 2012, traveled with family", "text": "great location; 2 blocks from leblon beach, lots of restaurants & shops, the nearest supermarket is called pao de asucar about 3 blocks away. most importantly this is a safe area in rio.", "title": "Very Central but only 40% of the rooms belong to the hotel..many strangers!", "helpfulness": 2, "user": "Finsy", "date": "January 5, 2012", "detail_rating": {"service": 3.0, "cleanliness": 3.0, "value": 1.0, "sleep": 4.0, "rooms": 2.0, "location": 4.0}, "id": 122607976}, {"rating": 3.0, "stay_parameters": "Stayed December 2011", "text": "2 shower-rooms, a rare finding", "title": "Location, location, location", "helpfulness": 1, "user": "jmusman", "date": "December 30, 2011", "detail_rating": {"cleanliness": 3.0, "value": 2.0, "location": 5.0, "service": 3.0, "rooms": 2.0}, "id": 122288462}, {"rating": 2.0, "stay_parameters": "Stayed November 2012, traveled as a couple", "text": "Stayed for two nights with my wife. The hotel is well located if you want the beach and shopping, but Leblon isn't that good if you want to go e.g. to Christ or Sugar Loaf, and the metro hasn't got there yet.", "title": "Agree with previous posters", "helpfulness": 1, "user": "JeffStranks", "date": "November 8, 2012", "detail_rating": {"service": 3.0, "cleanliness": 4.0, "value": 2.0, "sleep": 2.0, "rooms": 2.0, "location": 3.0}, "id": 144926288}, {"rating": 2.0, "stay_parameters": "Stayed August 2012, traveled with friends", "text": "Didn't have great expectations after reading older comments here. We liked the cleanliness and the attitude of the staff, plus the size of the room (it's an apartment). But:", "title": "Good location- but that's it", "helpfulness": 1, "user": "Seamone B", "date": "October 13, 2012", "detail_rating": {"service": 2.0, "cleanliness": 2.0, "value": 1.0, "sleep": 2.0, "rooms": 2.0, "location": 3.0}, "id": 142749498}], "location": {"country": "Brazil", "continent": "South America", "city": "Rio de Janeiro"}, "stars": 3.5, "variance": {"poor": 56, "average": 107, "very good": 78, "terrible": 25, "excellent": 28}, "aka": "Mercure Apartments Rio De Janeiro Leblon Hotel", "slim_ranking": 0.666666666667, "description": "The Mercure Leblon hotel is located in one of Rio's most charming districts, close to Antero de Quental square and Ataulfo de Paiva and Bartolemeu Mitre avenues. It is surrounded by various bars, restaurants and shops, in addition to the Rio Design and Leblon shopping centers.*We would like to inform guests that the hotel will be undergoing renovation work on apartments, communal areas, elevators and pipework until March 2014."}