{"user_rating": 4.5, "review_count": 359, "name": "Hotel Tilsitt Etoile Paris", "reviews": [{"rating": 5.0, "stay_parameters": "Stayed March 2008, traveled with friends", "text": "Good location, good breakfast and good service. for a weekend", "title": "Great Service", "helpfulness": 1, "user": "mchelenblue", "date": "April 7, 2008", "detail_rating": {"cleanliness": 5.0, "front_desk": 5.0, "location": 5.0, "value": 5.0, "rooms": 4.0}, "id": 14849978, "likes": {"liked": "\u2014 Friendly staff", "disliked": "\u2014 Nothing"}}, {"rating": 5.0, "stay_parameters": "Stayed March 2008, traveled as a couple", "text": "for three women sharing a room.", "title": "Wonderfully charming hotel", "helpfulness": 2, "user": "trixy24", "date": "April 4, 2008", "detail_rating": {"front_desk": 5.0, "business": 5.0, "service": 5.0, "cleanliness": 5.0, "value": 5.0, "location": 5.0, "rooms": 5.0}, "id": 14786608, "likes": {"liked": "\u2014 the decor and the staff (and the croissants)", "disliked": "\u2014 nothing"}}, {"rating": 5.0, "stay_parameters": "Stayed March 2008, traveled as a couple", "text": "The beds were clean and comfortable and the towels white and fluffy.", "title": "Fantastic service, friendly staff, great location, loved it!", "helpfulness": 1, "user": "Romeo&Juliette", "date": "March 31, 2008", "detail_rating": {"front_desk": 5.0, "service": 5.0, "cleanliness": 5.0, "value": 5.0, "rooms": 4.0, "location": 4.0}, "id": 14690275, "likes": {"liked": "\u2014 The service"}}, {"rating": 5.0, "stay_parameters": "Stayed March 2008, traveled with family", "text": "There were no tea/coffee making facilities in the room, however,", "title": "Really enjoyed our stay at Hotel Tilsitt Etoile Paris", "user": "Helenishka", "date": "March 31, 2008", "detail_rating": {"front_desk": 5.0, "business": 5.0, "service": 5.0, "cleanliness": 5.0, "value": 5.0, "location": 5.0, "rooms": 5.0}, "id": 14678516, "likes": {"liked": "\u2014 location", "disliked": "\u2014 nothing"}}, {"rating": 5.0, "stay_parameters": "Stayed March 2008, traveled with family", "text": "when we requested a kettle, this was provided at no extra cost", "title": "Charming hotel, great location", "helpfulness": 1, "user": "linduguapa", "date": "March 30, 2008", "detail_rating": {"front_desk": 5.0, "business": 5.0, "service": 5.0, "cleanliness": 5.0, "value": 5.0, "location": 5.0, "rooms": 5.0}, "id": 14656660, "likes": {"liked": "\u2014 Front desk staff, charming hotel, heated towel rack, wonderful breakfast", "disliked": "\u2014 somewhat thin walls between rooms"}}, {"rating": 5.0, "stay_parameters": "Stayed March 2008, traveled on business", "text": "I stayed here with my girlfriend and my parents for the easter weekend.", "title": "Great hotel", "helpfulness": 3, "user": "Gilamonyet", "date": "March 24, 2008", "detail_rating": {"front_desk": 5.0, "business": 4.0, "service": 5.0, "cleanliness": 5.0, "value": 5.0, "location": 5.0, "rooms": 5.0}, "id": 14505480, "likes": {"liked": "\u2014 Behind the desk staff", "disliked": "\u2014 -"}}, {"rating": 4.0, "stay_parameters": "Stayed March 2008, traveled as a couple", "text": "This hotel is great its close to the Arc de Triomphe and the Champs Elysees. While being close to such heavily visited things in Paris youre staying in a peacefull street so no loud noise from outside or what so ever.", "title": "Very Good Value", "helpfulness": 2, "user": "TheRoyOfTheRovers", "date": "March 21, 2008", "detail_rating": {"front_desk": 4.0, "business": 3.0, "service": 5.0, "cleanliness": 4.0, "value": 4.0, "location": 3.0, "rooms": 4.0}, "id": 14436940, "likes": {"liked": "\u2014 cleanliness; bathroom; service; breakfast", "disliked": "\u2014 -"}}, {"rating": 5.0, "stay_parameters": "Stayed January 2008, traveled on business", "text": "The rooms arent big but there great for couples. It was more cozy then it was annoying. Also at the arrival the rooms where nicely cleaned and the mini bar was filled with enough drinks. Enough towels, soap and a VERY clean bathroom!", "title": "Great personnal service and tourism information!!", "helpfulness": 2, "user": "tools99", "date": "March 21, 2008", "detail_rating": {"front_desk": 5.0, "business": 5.0, "service": 5.0, "cleanliness": 5.0, "value": 4.0, "location": 5.0, "rooms": 4.0}, "id": 14428763, "likes": {"liked": "\u2014 The Front desk service and location!", "disliked": "\u2014 N/A"}}, {"rating": 5.0, "title": "Consistently Excellent", "text": "The breakfast was great. Alot of different food you can eat such as fruit, yogurt, bread, croissaints and some other france delights. Also there's a constant supply of Jus d'orange while having breakfast. They even made a 'special dishes' because it was easter", "helpfulness": 2, "user": "BrownsFan40", "date": "March 20, 2008", "id": 14409517}, {"rating": 5.0, "stay_parameters": "Stayed March 2008, traveled with friends", "text": "The staff was very friendly and helpfull. The staff that worked at kitchen for breakfast worked really hard to keep the supply of food constant and they also were very friendly if you asked for something else.", "title": "Fantastic Hotel in Paris", "helpfulness": 2, "user": "BredaK", "date": "March 12, 2008", "detail_rating": {"front_desk": 5.0, "business": 3.0, "service": 5.0, "cleanliness": 5.0, "value": 5.0, "location": 5.0, "rooms": 5.0}, "id": 14244900, "likes": {"liked": "\u2014 Location", "disliked": "\u2014 Room Size"}}, {"rating": 5.0, "stay_parameters": "Stayed February 2008, traveled with friends", "text": "Great price, excellent breakfast, great rooms, and very helpful nice staff! Loved the 24-hour bar area and hotel is very close to everything! Would definitely stay again.", "title": "Love It!", "user": "kchuscavage", "date": "February 26, 2008", "detail_rating": {"front_desk": 5.0, "business": 5.0, "service": 5.0, "cleanliness": 5.0, "value": 5.0, "location": 4.0, "rooms": 4.0}, "id": 13855488, "likes": {"liked": "\u2014 The reception staff and the breakfast", "disliked": "\u2014 Nothing"}}, {"rating": 5.0, "title": "Like your home But in Paris", "text": "Great service , full service , excelent facilities inside and around the hotel , few steps from main turistcs points and main subway stations , estrategicaly located.", "user": "FonsecaBrazil", "date": "February 24, 2008", "id": 13799891}, {"rating": 5.0, "stay_parameters": "Stayed February 2008, traveled with family", "text": "We chose this hotel for a 2 day family stay due to its excellent reviews. I'm pleased to say these are well deserved.", "title": "Ideal Paris Base", "helpfulness": 3, "user": "redletterday", "date": "February 20, 2008", "detail_rating": {"front_desk": 5.0, "service": 5.0, "cleanliness": 5.0, "value": 4.0, "rooms": 5.0, "location": 4.0}, "id": 13717303}, {"rating": 4.0, "stay_parameters": "Stayed January 2008, traveled on business", "text": "The hotel is easy to find and not too far from the Charles de Gaulle Metro station (downhill on the way there). The staff were friendly and welcoming, but not intrusive. Access to rooms via the lift was good, and the size of our rooms on the 6th floor was good (for Paris) I was worried that the room might be cold, on the top floor under the tiles, but need not have worried, and we unplugged the extra, electric radiator supplied. The room was clean and the bed comfortable with attractive clean linen. The bathroom was fine, although water pressure on the 6th floor wasn't powerful in the shower.", "title": "Great price/quality ratio", "user": "ManuelMilano", "date": "February 20, 2008", "detail_rating": {"front_desk": 4.0, "business": 4.0, "service": 5.0, "cleanliness": 5.0, "value": 4.0, "location": 5.0, "rooms": 4.0}, "id": 13697644, "likes": {"liked": "\u2014 Cleaniness and friendly staff.", "disliked": "\u2014 Space"}}, {"rating": 4.0, "stay_parameters": "Stayed February 2008, traveled as a couple", "text": "We opted for breakfast in the charming basement breakfast room, maybe slightly expensive at 13euro but delicious especially the orange juice and coffee.", "title": "So wonderful!!", "helpfulness": 2, "user": "alq1984", "date": "February 17, 2008", "detail_rating": {"front_desk": 5.0, "business": 4.0, "service": 5.0, "cleanliness": 4.0, "value": 4.0, "location": 4.0, "rooms": 4.0}, "id": 13619031, "likes": {"liked": "\u2014 The people, the room, the location, the decor", "disliked": "\u2014 hearing the people next to us at 2 a.m."}}, {"rating": 5.0, "title": "Large rooms, great location and super price", "text": "Wifi worked, breakfast was delivered to our room and it was good. I really liked how our room had a split bathroom. Take a look at our pictures :) It's a very family friendly place and we stayed at other hotels in paris and you will not find this kind of room at this price.", "user": "RosemaryNoriega", "date": "January 25, 2008", "id": 12984600}, {"rating": 4.0, "stay_parameters": "Stayed January 2008", "text": "We found that there was no need for a view, our room was nicely lit with natural diffused light.", "title": "Reasonably priced, brilliant area", "helpfulness": 2, "user": "TravellingChic", "date": "January 20, 2008", "detail_rating": {"front_desk": 3.0, "business": 3.0, "service": 3.0, "cleanliness": 4.0, "value": 4.0, "location": 4.0, "rooms": 4.0}, "id": 12826322}, {"rating": 5.0, "stay_parameters": "Stayed December 2007, traveled as a couple", "text": "My partner and I stayed at the Tilsitt hotel in Jan 08. We were pleasantly surprised by the interior.", "title": "Great Hotel", "helpfulness": 1, "user": "Ali86", "date": "January 7, 2008", "detail_rating": {"front_desk": 5.0, "business": 4.0, "service": 5.0, "cleanliness": 5.0, "value": 5.0, "location": 5.0, "rooms": 5.0}, "id": 12404392, "likes": {"liked": "\u2014 The location", "disliked": "\u2014 slow lift"}}, {"rating": 4.0, "title": "Home feel Hotel", "text": "The reception room leads to the bar lounge area, which is very nicely decorated. Although we rarely saw a bar tender present.", "user": "Yvette1203", "date": "December 14, 2007", "id": 11538062}, {"rating": 4.0, "title": "Best placed but not best priced.", "text": "The lift is very small so bear this in mind if you have lots of luggage. We only stayed a night so it wasn't a problem. If you walk down the stairs, you'll notice the hard wood floors on the ground floor. Really lovely.", "helpfulness": 2, "user": "chau7", "date": "December 11, 2007", "id": 11487104}], "location": {"country": "France", "region": "Ile-de-France", "continent": "Europe", "city": "Paris"}, "stars": 3, "variance": {"poor": 7, "average": 28, "very good": 150, "terrible": 3, "excellent": 171}, "aka": "Tilsitt Etoile", "slim_ranking": 0.256553262688, "description": "Two steps away from the Champs Elysees, the Arc de triomphe and the Palais des Congres, this charming 3 stars design hotel is the perfect place to stay, right in the heart of Paris..."}