{"user_rating": 4.5, "review_count": 15, "name": "Powerhouse Apartments & Terraces", "reviews": [{"rating": 5.0, "stay_parameters": "Stayed November 2007, traveled on business", "text": "This has to be the best value hotel in Brisbane. I booked it as I was staying for a week, wanted a bit of extra space and didn't want to stay in a big chain hotel. At $120 a night it was half the price of the big business hotels.", "title": "Spacious, Friendly and Great Value", "helpfulness": 2, "user": "Riesling", "date": "January 10, 2008", "detail_rating": {"front_desk": 5.0, "business": 4.0, "service": 5.0, "cleanliness": 5.0, "value": 5.0, "location": 5.0, "rooms": 5.0}, "id": 12501870, "likes": {"liked": "\u2014 Space and value", "disliked": "\u2014 Nothing"}}], "location": {"country": "Australia", "continent": "South Pacific", "city": "Brisbane"}, "variance": {"poor": 2, "average": 1, "very good": 3, "terrible": 0, "excellent": 9}, "aka": "Powerhouse Apartments And Terraces", "slim_ranking": 0.48275862069}