{"user_rating": 3.5, "review_count": 645, "name": "Ramada Plaza Toronto Downtown", "reviews": [{"rating": 3.0, "stay_parameters": "Stayed June 2007, traveled with friends", "text": "Stayed for 5 nights on holiday in Toronto. Staff were not especially friendly at check in, but warmed up as the stay went on thankfully. Actually they turned out to be some of the politer people we met in Toronto so I am not complaining.", "title": "OK Hotel", "helpfulness": 2, "user": "Trav-london", "date": "June 21, 2007", "detail_rating": {"front_desk": 3.0, "business": 4.0, "service": 2.0, "cleanliness": 4.0, "value": 3.0, "location": 2.0, "rooms": 4.0}, "id": 7958427, "likes": {"liked": "\u2014 Comfortable bed", "disliked": "\u2014 Slow lifts"}}, {"rating": 5.0, "title": "A Suite Time!", "text": "Room was modern & clean as you would expect. Lifts from the 10th floor could be annoying slow at peak times (i.e. stopping every floor).", "helpfulness": 19, "user": "FuntimesOwenSound_ON", "date": "June 19, 2007", "id": 7938441}, {"rating": 5.0, "stay_parameters": "Stayed June 2007, traveled on business", "text": "The restaurant/breakfast room is drab and uninspiring, with poor natural light. I had breakfast there once and did not return.", "title": "Our favorite hotel in Toronto", "helpfulness": 19, "user": "MrPanther", "date": "June 19, 2007", "detail_rating": {"front_desk": 5.0, "business": 5.0, "service": 5.0, "cleanliness": 5.0, "value": 5.0, "location": 5.0, "rooms": 4.0}, "id": 7936600, "likes": {"liked": "\u2014 please see our review", "disliked": "\u2014 nothing negative"}}, {"rating": 4.0, "title": "Most enjoyable stay", "text": "The fitness room is well equipped, but the pool is on the small side.", "helpfulness": 18, "user": "bjack", "date": "June 9, 2007", "id": 7817011}], "location": {"country": "Canada", "city": "Toronto"}, "stars": 3, "variance": {"poor": 61, "average": 147, "very good": 249, "terrible": 42, "excellent": 146}, "aka": "Ramada Plaza Toronto Hotel Toronto", "slim_ranking": 0.446808510638}